krx_analysis/__init__.py
krx_analysis/dictionary.py
krx_analysis/models.py
krx_analysis/modelschema.py
krx_analysis/mongo.py
krx_analysis/parser.py
krx_analysis/viewer.py
krx_analysis/data/__init__.py
krx_analysis/data/data_collector.py
krx_analysis/data/menutree.py
krx_analysis/data/req.py
krx_analysis/indices/__init__.py
krx_analysis/open/__init__.py
krx_analysis/open/data_collector.py
krx_analysis/open/menutree.py
krx_analysis/open/req.py
krxdata/__init__.py
krxdata/holiday.py
krxdata-2.0.0.dist-info/METADATA
krxdata-2.0.0.dist-info/WHEEL
krxdata-2.0.0.dist-info/top_level.txt
krxdata-2.0.0.dist-info/RECORD
