Metadata-Version: 2.1
Name: krxdata
Version: 2.0.0
Summary: 한국거래소 데이터 API
Home-page: https://github.com/innovata/KrxDataAPI
Author: innovata
Author-email: iinnovata@gmail.com
Classifier: Programming Language :: Python :: 3
Classifier: License :: OSI Approved :: MIT License
Classifier: Operating System :: OS Independent
Requires-Python: >=3.9
Requires-Dist: ipylib
Requires-Dist: holidays
Requires-Dist: pandas
Requires-Dist: xlrd
Requires-Dist: openpyxl
Requires-Dist: requests
